LICENSE
MANIFEST.in
README.md
setup.py
tudou.egg-info/PKG-INFO
tudou.egg-info/SOURCES.txt
tudou.egg-info/dependency_links.txt
tudou.egg-info/top_level.txt
tudouNLP/__init__.py
tudouNLP/models/__init__.py
tudouNLP/models/bert_config.json
tudouNLP/models/label2id.pkl
tudouNLP/models/modeling.py
tudouNLP/models/ner.pkl
tudouNLP/models/optimization.py
tudouNLP/models/pos_tag.pkl
tudouNLP/models/pos_tag.py
tudouNLP/models/predict.py
tudouNLP/models/run_classifier.py
tudouNLP/models/sentence.py
tudouNLP/models/tf_metrics.py
tudouNLP/models/tokenization.py
tudouNLP/models/train.py
tudouNLP/models/vocab.txt
tudouNLP/tools/__init__.py
tudouNLP/tools/compress_ckpt.py
tudouNLP/tools/convert_taggeddata_to_bert_taggeddata.py
tudouNLP/tools/convert_to_tagdata.py
tudouNLP/tools/get_ner_labels.py
tudouNLP/tools/ner_predict_utils.py
tudouNLP/tools/sentiment_predict_utils.py
tudouNLP/tools/tag_predict_utils.py
tudouNLP/tools/utils.py