Metadata-Version: 1.0
Name: tudou
Version: 2.0.1
Summary: A Chinese NLP tools based Google-bert
Home-page: UNKNOWN
Author: fennuDetudou
Author-email: upczyxl@163.com
License: MIT
Keywords: bert nlp ner NER named entity recognition tensorflow machine learning sentence encoding embedding pos tag sentiment judge
Platform: UNKNOWN
